schemapin/__init__.py
schemapin/core.py
schemapin/crypto.py
schemapin/discovery.py
schemapin/interactive.py
schemapin/pinning.py
schemapin/utils.py
tools/__init__.py
tools/keygen.py
tools/schema_signer.py
tools/verify_schema.py
schemapin-1.1.4.dist-info/METADATA
schemapin-1.1.4.dist-info/WHEEL
schemapin-1.1.4.dist-info/entry_points.txt
schemapin-1.1.4.dist-info/top_level.txt
schemapin-1.1.4.dist-info/RECORD
