Metadata-Version: 2.4
Name: schemapin
Version: 1.1.4
Summary: Cryptographic schema integrity verification for AI tools
Home-page: https://github.com/thirdkey/schemapin
Author: ThirdKey
Author-email: ThirdKey <contact@thirdkey.ai>
Maintainer: Jascha Wanger
Maintainer-email: Jascha Wanger <jascha@thirdkey.ai>
License: MIT
Project-URL: Homepage, https://github.com/thirdkey/schemapin
Project-URL: Repository, https://github.com/thirdkey/schemapin
Project-URL: Documentation, https://github.com/thirdkey/schemapin/blob/main/README.md
Project-URL: Bug Tracker, https://github.com/thirdkey/schemapin/issues
Project-URL: Changelog, https://github.com/thirdkey/schemapin/blob/main/CHANGELOG.md
Keywords: cryptography,schema,verification,ecdsa,ai-tools,security,digital-signatures,key-pinning,mcp,tool-integrity
Platform: any
Classifier: Development Status :: 4 - Beta
Classifier: Intended Audience :: Developers
Classifier: Intended Audience :: System Administrators
Classifier: License :: OSI Approved :: MIT License
Classifier: Operating System :: OS Independent
Classifier: Programming Language :: Python :: 3
Classifier: Programming Language :: Python :: 3.8
Classifier: Programming Language :: Python :: 3.9
Classifier: Programming Language :: Python :: 3.10
Classifier: Programming Language :: Python :: 3.11
Classifier: Programming Language :: Python :: 3.12
Classifier: Topic :: Security :: Cryptography
Classifier: Topic :: Software Development :: Libraries :: Python Modules
Classifier: Topic :: Internet :: WWW/HTTP :: HTTP Servers
Classifier: Topic :: System :: Systems Administration :: Authentication/Directory
Classifier: Typing :: Typed
Requires-Python: >=3.8
Requires-Dist: cryptography==44.0.1
Requires-Dist: requests==2.32.3
Provides-Extra: dev
Requires-Dist: pytest==7.4.4; extra == "dev"
Requires-Dist: pytest-cov==4.1.0; extra == "dev"
Requires-Dist: ruff==0.8.4; extra == "dev"
Requires-Dist: bandit==1.8.0; extra == "dev"
Requires-Dist: mypy==1.13.0; extra == "dev"
Requires-Dist: black==24.10.0; extra == "dev"
Provides-Extra: test
Requires-Dist: pytest>=7.4.0; extra == "test"
Requires-Dist: pytest-cov>=4.1.0; extra == "test"
Provides-Extra: docs
Requires-Dist: sphinx>=7.0.0; extra == "docs"
Requires-Dist: sphinx-rtd-theme>=1.3.0; extra == "docs"
Dynamic: author
Dynamic: home-page
Dynamic: requires-python
